qrcode_scanner/__init__.py
qrcode_scanner/exceptions.py
qrcode_scanner-0.0.4.dist-info/METADATA
qrcode_scanner-0.0.4.dist-info/WHEEL
qrcode_scanner-0.0.4.dist-info/RECORD
