Metadata-Version: 2.1
Name: qrcode-scanner
Version: 0.0.4
Summary: Read QR codes from HID devices
Home-page: https://github.com/medram/qrcode-scanner
Keywords: Qr Code,qr code scanner,hid,usb qr code scanner,qrcode scanner,hidapi
Author: medram
Author-email: mramouchy@gmail.com
Requires-Python: >=3.10,<4.0
Classifier: Programming Language :: Python :: 3
Classifier: Programming Language :: Python :: 3.10
Classifier: Programming Language :: Python :: 3.11
Classifier: Programming Language :: Python :: 3.12
Requires-Dist: hidapi (>=0.14.0.post4,<0.15.0)
Requires-Dist: pyserial (>=3.5,<4.0)
Project-URL: Documentation, https://github.com/medram/qrcode-scanner
Project-URL: Repository, https://github.com/medram/qrcode-scanner
